{
  "generated_at": "2026-04-29T03:30:11.717797-07:00",
  "generated_tz": "PDT",
  "month": "2026-04",
  "month_label": "April 2026",
  "day": 29,
  "month_days": 30,
  "goals": {
    "Low Ticket Funnel": 200,
    "Instagram": 300,
    "VSL": 200,
    "YouTube": 80,
    "Internal Webinar": 70,
    "Website": 100,
    "X": 10,
    "Linkedin": 10,
    "Newsletter": 10,
    "TikTok": 5,
    "Side Hustle Nation": 1,
    "WWWS": 1
  },
  "summary": {
    "mtd_booked": 812,
    "on_pace": 954,
    "remaining": 175,
    "eom_projection": 840,
    "total_goal": 987,
    "closed_won_mtd": 0,
    "inhouse": {
      "total": 328,
      "showed": 194,
      "qualified": 145
    },
    "external": {
      "total": 484,
      "showed": 304,
      "qualified": 242
    }
  },
  "by_funnel": {
    "Instagram": {
      "total": 260,
      "showed": 158,
      "qualified": 125
    },
    "LTF - Quiz Funnel": {
      "total": 4,
      "showed": 1,
      "qualified": 1
    },
    "Low Ticket Funnel": {
      "total": 185,
      "showed": 122,
      "qualified": 96
    },
    "Internal Webinar": {
      "total": 68,
      "showed": 29,
      "qualified": 24
    },
    "Meta Ads": {
      "total": 36,
      "showed": 17,
      "qualified": 14
    },
    "Unknown (Needs Review)": {
      "total": 6,
      "showed": 3,
      "qualified": 1
    },
    "Website": {
      "total": 56,
      "showed": 43,
      "qualified": 34
    },
    "X": {
      "total": 10,
      "showed": 6,
      "qualified": 9
    },
    "YouTube": {
      "total": 122,
      "showed": 84,
      "qualified": 61
    },
    "VSL": {
      "total": 29,
      "showed": 6,
      "qualified": 4
    },
    "Website - OG - Cam": {
      "total": 2,
      "showed": 1,
      "qualified": 1
    },
    "Linkedin": {
      "total": 14,
      "showed": 10,
      "qualified": 6
    },
    "Reactivation Scrapers": {
      "total": 3,
      "showed": 3,
      "qualified": 1
    },
    "WWWS": {
      "total": 7,
      "showed": 6,
      "qualified": 3
    },
    "Reactivation Email": {
      "total": 5,
      "showed": 4,
      "qualified": 4
    },
    "LinkedIn Ads": {
      "total": 2,
      "showed": 2,
      "qualified": 2
    },
    "Passivepreneurs": {
      "total": 1,
      "showed": 1,
      "qualified": 0
    },
    "Referred": {
      "total": 1,
      "showed": 1,
      "qualified": 1
    },
    "Mike Newsletter": {
      "total": 1,
      "showed": 1,
      "qualified": 0
    }
  },
  "by_funnel_day": {
    "Instagram": {
      "29": 16,
      "28": 15,
      "27": 11,
      "24": 10,
      "23": 15,
      "21": 14,
      "22": 16,
      "20": 13,
      "17": 13,
      "15": 10,
      "16": 10,
      "14": 17,
      "13": 17,
      "10": 13,
      "9": 11,
      "8": 17,
      "7": 11,
      "6": 9,
      "3": 9,
      "1": 5,
      "2": 8
    },
    "LTF - Quiz Funnel": {
      "28": 2,
      "29": 2
    },
    "Low Ticket Funnel": {
      "28": 6,
      "29": 9,
      "27": 7,
      "24": 6,
      "23": 14,
      "22": 5,
      "21": 6,
      "20": 4,
      "18": 2,
      "16": 10,
      "15": 11,
      "17": 9,
      "14": 7,
      "13": 4,
      "11": 1,
      "9": 11,
      "10": 8,
      "8": 17,
      "7": 17,
      "6": 5,
      "3": 6,
      "2": 10,
      "1": 10
    },
    "Internal Webinar": {
      "28": 4,
      "29": 1,
      "27": 2,
      "23": 5,
      "24": 4,
      "22": 2,
      "25": 1,
      "21": 2,
      "20": 4,
      "16": 3,
      "15": 3,
      "13": 4,
      "14": 2,
      "9": 10,
      "10": 2,
      "8": 6,
      "7": 3,
      "6": 2,
      "3": 2,
      "2": 2,
      "1": 4
    },
    "Meta Ads": {
      "28": 3,
      "29": 1,
      "27": 2,
      "23": 3,
      "22": 1,
      "24": 4,
      "21": 2,
      "20": 1,
      "17": 1,
      "16": 1,
      "15": 2,
      "13": 4,
      "14": 2,
      "10": 1,
      "9": 1,
      "8": 1,
      "6": 1,
      "3": 2,
      "2": 1,
      "1": 2
    },
    "Unknown (Needs Review)": {
      "27": 1,
      "28": 1,
      "10": 1,
      "9": 2,
      "3": 1
    },
    "Website": {
      "28": 3,
      "29": 5,
      "23": 4,
      "22": 4,
      "24": 3,
      "21": 4,
      "17": 4,
      "20": 1,
      "16": 3,
      "15": 2,
      "13": 4,
      "14": 2,
      "10": 4,
      "9": 1,
      "7": 4,
      "6": 5,
      "3": 1,
      "1": 2
    },
    "X": {
      "29": 1,
      "28": 1,
      "24": 1,
      "8": 1,
      "10": 1,
      "7": 1,
      "6": 1,
      "3": 2,
      "1": 1
    },
    "YouTube": {
      "28": 3,
      "29": 7,
      "24": 6,
      "27": 7,
      "22": 5,
      "21": 8,
      "23": 4,
      "20": 9,
      "15": 11,
      "16": 2,
      "17": 1,
      "14": 3,
      "13": 9,
      "9": 5,
      "10": 1,
      "8": 8,
      "7": 6,
      "6": 9,
      "3": 5,
      "2": 7,
      "1": 6
    },
    "VSL": {
      "29": 1,
      "28": 3,
      "27": 3,
      "22": 4,
      "24": 1,
      "21": 2,
      "18": 1,
      "20": 2,
      "17": 3,
      "15": 1,
      "14": 5,
      "10": 2,
      "9": 1
    },
    "Website - OG - Cam": {
      "29": 1,
      "16": 1
    },
    "Linkedin": {
      "28": 1,
      "27": 1,
      "24": 1,
      "21": 1,
      "17": 2,
      "13": 1,
      "15": 1,
      "14": 2,
      "9": 1,
      "8": 1,
      "6": 1,
      "3": 1
    },
    "Reactivation Scrapers": {
      "21": 1,
      "16": 1,
      "10": 1
    },
    "WWWS": {
      "21": 1,
      "17": 2,
      "13": 2,
      "9": 1,
      "10": 1
    },
    "Reactivation Email": {
      "17": 1,
      "6": 2,
      "3": 1,
      "1": 1
    },
    "LinkedIn Ads": {
      "17": 1,
      "13": 1
    },
    "Passivepreneurs": {
      "1": 1
    },
    "Referred": {
      "3": 1
    },
    "Mike Newsletter": {
      "1": 1
    }
  },
  "won_by_funnel": {}
}